xdantic/__init__.py
xdantic/xdantic.py
xdantic-0.1.0.dist-info/LICENSE
xdantic-0.1.0.dist-info/WHEEL
xdantic-0.1.0.dist-info/METADATA
xdantic-0.1.0.dist-info/RECORD
