Metadata-Version: 2.1
Name: xdantic
Version: 0.1.0
Summary: A lightweight Python config library on top of Pydantic.
Author-email: Sebastian Lettner <sebastian.a.lettner@gmail.com>
Requires-Python: >=3.10
Classifier: Programming Language :: Python :: 3
Classifier: Operating System :: OS Independent
Requires-Dist: pydantic[dotenv]==2.6.*
Requires-Dist: pydantic-settings==2.2.*
Requires-Dist: pyyaml>=6.0
Requires-Dist: mkdocs-material ; extra == "docs"
Requires-Dist: mkdocstrings[python-legacy]>=0.18 ; extra == "docs"
Requires-Dist: mkdocs-gen-files>=0.4.0 ; extra == "docs"
Requires-Dist: mkdocs-literate-nav>=0.6.0 ; extra == "docs"
Requires-Dist: pytest ; extra == "testing"
Requires-Dist: pytest-pep8 ; extra == "testing"
Requires-Dist: pytest-cov ; extra == "testing"
Requires-Dist: black==22.6.0 ; extra == "testing"
Requires-Dist: isort==5.8.0 ; extra == "testing"
Requires-Dist: flake8==4.0.1 ; extra == "testing"
Requires-Dist: pre-commit ; extra == "testing"
Requires-Dist: nbconvert~=7.2.2 ; extra == "testing"
Requires-Dist: jupyter~=1.0.0 ; extra == "testing"
Requires-Dist: bumpversion ; extra == "testing"
Provides-Extra: docs
Provides-Extra: testing
